core.py
embed.py
mcp_server.py
clip/clip.py
clip/convert.py
clip/hf_preproc.py
clip/image_processor.py
clip/linear_probe.py
clip/model.py
clip/test.py
clip/tokenizer.py
local_image_search-0.2.4.dist-info/METADATA
local_image_search-0.2.4.dist-info/WHEEL
local_image_search-0.2.4.dist-info/entry_points.txt
local_image_search-0.2.4.dist-info/top_level.txt
local_image_search-0.2.4.dist-info/RECORD
