Metadata-Version: 2.4
Name: local-image-search
Version: 0.2.4
Summary: MCP server for local image search using CLIP embeddings
Requires-Python: >=3.11
Requires-Dist: daft>=0.7.2
Requires-Dist: huggingface-hub>=0.36.0
Requires-Dist: mcp>=1.0.0
Requires-Dist: mlx>=0.30.3
Requires-Dist: numpy>=2.4.1
Requires-Dist: pillow>=12.1.0
Requires-Dist: pillow-heif>=1.1.1
Requires-Dist: pylance>=1.0.2
Requires-Dist: regex>=2024.0.0
Requires-Dist: torch>=2.9.1
Provides-Extra: dev
Requires-Dist: fastapi>=0.128.0; extra == "dev"
Requires-Dist: matplotlib>=3.10.8; extra == "dev"
Requires-Dist: uvicorn>=0.40.0; extra == "dev"
